cel2cli/__init__.py
cel2cli-0.0.1.dist-info/licenses/LICENSE
cel2cli-0.0.1.dist-info/METADATA
cel2cli-0.0.1.dist-info/WHEEL
cel2cli-0.0.1.dist-info/top_level.txt
cel2cli-0.0.1.dist-info/RECORD
