Metadata-Version: 2.4
Name: cel2cli
Version: 0.0.1
Summary: Common Expression Language for Agent Control (Placeholder - Coming Soon)
Author-email: CEL2CLI Team <info@cel2cli.com>
Project-URL: Homepage, https://cel2cli.com
Project-URL: Repository, https://github.com/cel2cli/cel2cli
Project-URL: Documentation, https://github.com/cel2cli/cel2cli
Project-URL: Bug Reports, https://github.com/cel2cli/cel2cli/issues
Classifier: Development Status :: 1 - Planning
Classifier: Intended Audience :: Developers
Classifier: Topic :: Software Development :: Libraries
Classifier: Programming Language :: Python :: 3
Classifier: Programming Language :: Python :: 3.11
Classifier: Programming Language :: Python :: 3.12
Classifier: License :: OSI Approved :: MIT License
Classifier: Operating System :: OS Independent
Requires-Python: >=3.11
License-File: LICENSE
Dynamic: license-file
